[
  {
    "name": "Garage",
    "address": "503 Colorado St, Austin, TX 78701",
    "latitude": 30.267967199999998,
    "longitude": -97.7440893,
    "rating": 4.5,
    "reviews": 908,
    "type": "Cocktail bar",
    "distance": 0.08,
    "placeId": "ChIJWdi3AAm1RIYRVOzVjpc3hOQ",
    "phone": "(512) 369-3490",
    "website": "http://www.garagetx.com/",
    "hours": "Closed · Opens 5 PM"
  },
  {
    "name": "The Dead Rabbit, Austin",
    "address": "204 E 6th St, Austin, TX 78701",
    "latitude": 30.267720699999998,
    "longitude": -97.7411286,
    "rating": 4.4,
    "reviews": 565,
    "type": "Bar",
    "distance": 0.12,
    "placeId": "ChIJW3sENn-1RIYRGjtbjA74zn0",
    "phone": "(737) 530-8830",
    "website": "http://www.thedeadrabbittx.com/",
    "hours": "Open · Closes 2 AM"
  },
  {
    "name": "Upstairs at Caroline",
    "address": "109 E 7th St, Austin, TX 78701",
    "latitude": 30.2686635,
    "longitude": -97.7420691,
    "rating": 4.9,
    "reviews": 6542,
    "type": "Bar",
    "distance": 0.12,
    "placeId": "ChIJQyfp5wm1RIYRuYHlan7PCQs",
    "phone": "(512) 982-6766",
    "website": "https://www.carolinerestaurant.com/upstairs-at-caroline?utm_source=google&utm_medium=organic&utm_campaign=business_listing",
    "hours": "Open · Closes 12 AM"
  },
  {
    "name": "Mort Subite European Bar",
    "address": "308 Congress Ave., Austin, TX 78701",
    "latitude": 30.265718,
    "longitude": -97.7439904,
    "rating": 4.7,
    "reviews": 1079,
    "type": "Bar",
    "distance": 0.12,
    "placeId": "ChIJi0ZEZwi1RIYRSpGdWA3gZiI",
    "phone": null,
    "website": "https://belgianbaraustin.com/",
    "hours": "Open · Closes 11 PM"
  },
  {
    "name": "Friends Bar",
    "address": "208 E 6th St, Austin, TX 78701",
    "latitude": 30.2676767,
    "longitude": -97.7409976,
    "rating": 4.6,
    "reviews": 1414,
    "type": "Live music bar",
    "distance": 0.13,
    "placeId": "ChIJiwdYeae1RIYRQmltbCQ80Mc",
    "phone": "(512) 320-8193",
    "website": "http://www.friendsbar.com/",
    "hours": "Open · Closes 2 AM"
  },
  {
    "name": "Firehouse Lounge",
    "address": "605 Brazos St, Austin, TX 78701",
    "latitude": 30.2681729,
    "longitude": -97.74108059999999,
    "rating": 4.5,
    "reviews": 1500,
    "type": "Cocktail bar",
    "distance": 0.14,
    "placeId": "ChIJ7XFDZae1RIYROB6oLNdB2Bk",
    "phone": "(512) 201-2522",
    "website": "https://www.firehousehostel.com/lounge",
    "hours": "Closed · Opens 5 PM"
  },
  {
    "name": "Gnar Bar",
    "address": "219 E 6th St, Austin, TX 78701",
    "latitude": 30.2672438,
    "longitude": -97.74080029999999,
    "rating": 4.4,
    "reviews": 202,
    "type": "Bar",
    "distance": 0.14,
    "placeId": "ChIJeycfXda1RIYRmiRkyZ_wiVs",
    "phone": "(512) 649-9693",
    "website": "http://www.gnarbaratx.com/",
    "hours": "Open · Closes 2 AM"
  },
  {
    "name": "Small Victory",
    "address": "108 E 7th St, Austin, TX 78701",
    "latitude": 30.268925999999997,
    "longitude": -97.7416927,
    "rating": 4.7,
    "reviews": 481,
    "type": "Bar",
    "distance": 0.15,
    "placeId": "ChIJKakp4Am1RIYRB-4OSSKKrPo",
    "phone": "(512) 903-9450",
    "website": "http://smallvictory.bar/",
    "hours": "Closed · Opens 5 PM"
  },
  {
    "name": "Azul Rooftop",
    "address": "310 E 5th St., Austin, TX 78701",
    "latitude": 30.266620099999997,
    "longitude": -97.7403752,
    "rating": 4.6,
    "reviews": 1156,
    "type": "Lounge bar",
    "distance": 0.17,
    "placeId": "ChIJVf7pl6e1RIYREEeVcaNdILo",
    "phone": "(512) 792-5647",
    "website": "https://www.azulrooftopatx.com/?utm_source=google&utm_medium=organic&utm_campaign=business_listing",
    "hours": "Open · Closes 10 PM"
  },
  {
    "name": "Bull's Irish Pub",
    "address": "607 San Jacinto Blvd, Austin, TX 78701",
    "latitude": 30.2677442,
    "longitude": -97.7400665,
    "rating": 4.8,
    "reviews": 131,
    "type": "Bar",
    "distance": 0.18,
    "placeId": "ChIJ93UN-Za1RIYRn6Y7Ix0cbbQ",
    "phone": "(512) 291-2748",
    "website": "http://bullsirishpub.com/",
    "hours": "Opens soon · 4 PM"
  },
  {
    "name": "San Jac Saloon",
    "address": "300 E 6th St, Austin, TX 78701",
    "latitude": 30.267581999999997,
    "longitude": -97.740155,
    "rating": 4.6,
    "reviews": 1112,
    "type": "Bar",
    "distance": 0.18,
    "placeId": "ChIJUa75Cqe1RIYR7k44LQvushI",
    "phone": "(512) 580-9136",
    "website": "http://www.sanjacsaloon.com/",
    "hours": "Open · Closes 2 AM"
  },
  {
    "name": "Midnight Cowboy",
    "address": "313 E 6th St, Austin, TX 78701",
    "latitude": 30.267086,
    "longitude": -97.7399698,
    "rating": 4.5,
    "reviews": 868,
    "type": "Cocktail bar",
    "distance": 0.19,
    "placeId": "ChIJT_Gwpqe1RIYRIZAT_hZguaQ",
    "phone": null,
    "website": "https://midnightcowboymodeling.com/",
    "hours": "Closed · Opens 5 PM"
  },
  {
    "name": "The Roosevelt Room",
    "address": "307 W 5th St, Austin, TX 78701",
    "latitude": 30.2677886,
    "longitude": -97.74627729999999,
    "rating": 4.6,
    "reviews": 2244,
    "type": "Cocktail bar",
    "distance": 0.19,
    "placeId": "ChIJIeohJQm1RIYRG-NyRBlsnuw",
    "phone": "(512) 494-4094",
    "website": "http://www.therooseveltroomatx.com/",
    "hours": "Open · Closes 12 AM"
  },
  {
    "name": "Corner Restaurant",
    "address": "110 E 2nd St, Austin, TX 78701",
    "latitude": 30.2645703,
    "longitude": -97.7438317,
    "rating": 4.8,
    "reviews": 17358,
    "type": "Bar",
    "distance": 0.19,
    "placeId": "ChIJxcCceAi1RIYR9AqXT8eWDyc",
    "phone": "(512) 608-4488",
    "website": "https://www.cornerrestaurantaustin.com/?utm_source=google&utm_medium=organic&utm_campaign=business_listing",
    "hours": "Open · Closes 12 AM"
  },
  {
    "name": "Edge Rooftop",
    "address": "110 E 2nd St, Austin, TX 78701",
    "latitude": 30.264396599999998,
    "longitude": -97.7438583,
    "rating": 4.9,
    "reviews": 5179,
    "type": "Bar",
    "distance": 0.2,
    "placeId": "ChIJIxradQi1RIYRjCgHBG2nRF8",
    "phone": "(512) 608-4503",
    "website": "https://www.edgerooftop.com/?utm_source=google&utm_medium=organic&utm_campaign=business_listing",
    "hours": "Closed · Opens 5 PM"
  },
  {
    "name": "Blind Pig Pub",
    "address": "317 E 6th St, Austin, TX 78701",
    "latitude": 30.2670732,
    "longitude": -97.7397914,
    "rating": 4.3,
    "reviews": 1340,
    "type": "Pub",
    "distance": 0.2,
    "placeId": "ChIJ36RepKe1RIYRaRHAMH0sZIo",
    "phone": "(512) 369-3358",
    "website": null,
    "hours": "Open · Closes 2 AM"
  },
  {
    "name": "Thirsty's",
    "address": "325 E 6th St, Austin, TX 78701",
    "latitude": 30.267024199999998,
    "longitude": -97.73954839999999,
    "rating": 3.8,
    "reviews": 407,
    "type": "Bar",
    "distance": 0.21,
    "placeId": "ChIJtRiMr6e1RIYReKRz5XFXRJM",
    "phone": "(512) 649-1232",
    "website": "http://thirstys6thstreet.com/",
    "hours": "Open · Closes 2 AM"
  },
  {
    "name": "Seven Grand",
    "address": "405 E 7th St, Austin, TX 78701",
    "latitude": 30.267697199999997,
    "longitude": -97.7386269,
    "rating": 4.7,
    "reviews": 695,
    "type": "Bar",
    "distance": 0.27,
    "placeId": "ChIJvYIs_6a1RIYRMcxe8rqXzNw",
    "phone": null,
    "website": "http://sevengrandaustin.com/",
    "hours": "Opens soon · 4 PM"
  },
  {
    "name": "Las Perlas",
    "address": "405 E 7th St, Austin, TX 78701",
    "latitude": 30.2676883,
    "longitude": -97.7386274,
    "rating": 4.6,
    "reviews": 361,
    "type": "Bar",
    "distance": 0.27,
    "placeId": "ChIJlYIs_6a1RIYR39hBxaq3BpY",
    "phone": null,
    "website": "http://lasperlasaustin.com/",
    "hours": "Opens soon · 4 PM"
  },
  {
    "name": "Zanzibar",
    "address": "304 E Cesar Chavez St, Austin, TX 78701",
    "latitude": 30.262830899999997,
    "longitude": -97.7415705,
    "rating": 4.8,
    "reviews": 8078,
    "type": "Restaurant",
    "distance": 0.32,
    "placeId": "ChIJFaJVsLS1RIYRcUZU0nlHQJ8",
    "phone": "(737) 787-6969",
    "website": "https://www.zanzibaratx.com/?utm_source=google&utm_medium=organic&utm_campaign=business_listing",
    "hours": "Open · Closes 12 AM"
  },
  {
    "name": "Unbarlievable West 6th",
    "address": "513 W 6th St, Austin, TX 78701",
    "latitude": 30.269289399999998,
    "longitude": -97.7480411,
    "rating": 3.1,
    "reviews": 54,
    "type": "Bar",
    "distance": 0.33,
    "placeId": "ChIJsyC4O0y1RIYR2ew8hrUk02A",
    "phone": "(512) 774-4311",
    "website": "https://www.unbarlievable.com/",
    "hours": "Open · Closes 5 PM"
  },
  {
    "name": "Kinfolk Cocktail Lounge & Spirits Library",
    "address": "303 B Red River St, Austin, TX 78701",
    "latitude": 30.264063399999998,
    "longitude": -97.7379309,
    "rating": 4.8,
    "reviews": 143,
    "type": "Bar",
    "distance": 0.38,
    "placeId": "ChIJMRK96Au1RIYRXr3K0DG7Ypc",
    "phone": "(512) 236-9687",
    "website": "https://kinfolkaustin.com/",
    "hours": "Closed · Opens 5 PM"
  },
  {
    "name": "Marlow",
    "address": "700 E 6th St, Austin, TX 78701",
    "latitude": 30.2663066,
    "longitude": -97.73586309999999,
    "rating": 4.8,
    "reviews": 142,
    "type": "Bar",
    "distance": 0.44,
    "placeId": "ChIJD1x5H3C1RIYRRtu34CzMXUw",
    "phone": null,
    "website": "https://marlow.bar/",
    "hours": "Closed · Opens 5 PM"
  },
  {
    "name": "Electric Shuffle Austin",
    "address": "91 Red River St STE 102, Austin, TX 78701",
    "latitude": 30.260507099999998,
    "longitude": -97.73902849999999,
    "rating": 4.7,
    "reviews": 380,
    "type": "Bar",
    "distance": 0.52,
    "placeId": "ChIJzbbxmGO1RIYRuZ6Zrc8aQuY",
    "phone": "(512) 894-8779",
    "website": "https://electricshuffle.com/us/austin",
    "hours": "Open · Closes 11 PM"
  },
  {
    "name": "Lustre Pearl Rainey",
    "address": "94 Rainey St, Austin, TX 78701",
    "latitude": 30.260662999999997,
    "longitude": -97.73823569999999,
    "rating": 4.2,
    "reviews": 485,
    "type": "Bar",
    "distance": 0.54,
    "placeId": "ChIJUz_DDam1RIYRm2VVEesZZp4",
    "phone": null,
    "website": "https://dunlapatx.com/lustre-pearl-rainey/",
    "hours": "Open · Closes 12 AM"
  },
  {
    "name": "The Drafting Room",
    "address": "88 1/2 Rainey St, Austin, TX 78701",
    "latitude": 30.2599032,
    "longitude": -97.73855669999999,
    "rating": 4.6,
    "reviews": 90,
    "type": "Cocktail bar",
    "distance": 0.57,
    "placeId": "ChIJkYCEdqm1RIYRUkrmaFu7TmA",
    "phone": null,
    "website": null,
    "hours": "Open · Closes 7 PM"
  },
  {
    "name": "Parlor Room",
    "address": "88 Rainey St, Austin, TX 78701",
    "latitude": 30.259862899999998,
    "longitude": -97.7386849,
    "rating": 4.2,
    "reviews": 333,
    "type": "Bar",
    "distance": 0.57,
    "placeId": "ChIJkYCEdqm1RIYROrwFIIeGXuE",
    "phone": "(512) 559-8800",
    "website": "http://parlorroomatx.com/",
    "hours": "Closed · Opens 5 PM Thu"
  },
  {
    "name": "Clive",
    "address": "609 Davis St, Austin, TX 78701",
    "latitude": 30.259997,
    "longitude": -97.738496,
    "rating": 4.3,
    "reviews": 640,
    "type": "Bar",
    "distance": 0.57,
    "placeId": "ChIJjazwc6m1RIYRBgKaR8VD_-0",
    "phone": null,
    "website": "https://dunlapatx.com/clive-bar/",
    "hours": "Opens soon · 4 PM"
  },
  {
    "name": "The Rainey House",
    "address": "76 Rainey St, Austin, TX 78701",
    "latitude": 30.2588829,
    "longitude": -97.7389673,
    "rating": 4.4,
    "reviews": 18,
    "type": "Bar & grill",
    "distance": 0.63,
    "placeId": "ChIJx105dd61RIYRAw2hFfe-ji0",
    "phone": "(512) 418-6128",
    "website": "http://rainey-house.com/",
    "hours": "Closed · Opens 6 PM"
  },
  {
    "name": "Half Step",
    "address": "75 1/2 Rainey St, Austin, TX 78701",
    "latitude": 30.258612999999997,
    "longitude": -97.73859399999999,
    "rating": 4.6,
    "reviews": 949,
    "type": "Cocktail bar",
    "distance": 0.65,
    "placeId": "ChIJx7Hw9qq1RIYR-Wd-iTGDcU4",
    "phone": "(512) 672-8698",
    "website": "http://halfstepbar.com/",
    "hours": "Opens soon · 4 PM"
  },
  {
    "name": "Lucille Patio Lounge",
    "address": "77 Rainey St, Austin, TX 78701",
    "latitude": 30.2587306,
    "longitude": -97.73854999999999,
    "rating": 4.4,
    "reviews": 921,
    "type": "Lounge bar",
    "distance": 0.65,
    "placeId": "ChIJUUPE1au1RIYRNr9jXMHCPIo",
    "phone": null,
    "website": "https://lucilleaustin.com/",
    "hours": "Opens soon · 4 PM"
  },
  {
    "name": "The Stay Put",
    "address": "73 Rainey St, Austin, TX 78701",
    "latitude": 30.258296599999998,
    "longitude": -97.738665,
    "rating": 4.6,
    "reviews": 157,
    "type": "Bar",
    "distance": 0.67,
    "placeId": "ChIJ0R3w3qq1RIYRJM0-nmntaIU",
    "phone": null,
    "website": "http://stayputatx.com/",
    "hours": "Open · Closes 12 AM"
  },
  {
    "name": "Violet Crown Social Club",
    "address": "1111 E 6th St, Austin, TX 78702",
    "latitude": 30.2642262,
    "longitude": -97.73076909999999,
    "rating": 4.4,
    "reviews": 488,
    "type": "Bar",
    "distance": 0.76,
    "placeId": "ChIJiSURHbC1RIYROqYkjckCVAs",
    "phone": "(512) 614-4461",
    "website": "http://violetcrownsocialclub.com/",
    "hours": "Opens soon · 4 PM"
  },
  {
    "name": "Industry",
    "address": "1211 E 5th St. Ste 150, Austin, TX 78702",
    "latitude": 30.2629956,
    "longitude": -97.7301213,
    "rating": 4.5,
    "reviews": 1264,
    "type": "Bar",
    "distance": 0.83,
    "placeId": "ChIJm1MeBQW1RIYR_x8s-YWWvzw",
    "phone": "(512) 564-8686",
    "website": "http://eastside.industrytx.com/",
    "hours": "Open · Closes 1 AM"
  },
  {
    "name": "Bar Mischief",
    "address": "1221 E 6th St, Austin, TX 78702",
    "latitude": 30.2639124,
    "longitude": -97.729725,
    "rating": 4.8,
    "reviews": 97,
    "type": "Bar",
    "distance": 0.83,
    "placeId": "ChIJAxuz1Ri1RIYR-L-cIHV45Ec",
    "phone": null,
    "website": "https://www.inncahoots.com/public-bars/bar-mischief",
    "hours": "Closed · Opens 6 PM Thu"
  },
  {
    "name": "Dive Bar Austin",
    "address": "1703 Guadalupe St, Austin, TX 78701",
    "latitude": 30.279892,
    "longitude": -97.742087,
    "rating": 4.5,
    "reviews": 422,
    "type": "Bar",
    "distance": 0.88,
    "placeId": "ChIJI8PZjXW1RIYRjmyX7kkdbas",
    "phone": "(512) 686-8325",
    "website": "https://divebaraustin.com/",
    "hours": "Open · Closes 2 AM"
  },
  {
    "name": "Nickel City",
    "address": "1133 E 11th St, Austin, TX 78702",
    "latitude": 30.268594699999998,
    "longitude": -97.72808289999999,
    "rating": 4.6,
    "reviews": 1271,
    "type": "Bar",
    "distance": 0.9,
    "placeId": "ChIJETpRB7u1RIYRDwQmAJdd-Wc",
    "phone": null,
    "website": "http://www.nickelcitybar.com/",
    "hours": "Open · Closes 2 AM"
  },
  {
    "name": "Seven Spirits",
    "address": "1411 E 7th St B, Austin, TX 78702",
    "latitude": 30.2641268,
    "longitude": -97.72740789999999,
    "rating": 4.7,
    "reviews": 106,
    "type": "Bar",
    "distance": 0.96,
    "placeId": "ChIJ_9hfBlq1RIYRxA2M9ARwrY8",
    "phone": null,
    "website": "http://www.sevenspiritsaustin.com/",
    "hours": "Opens soon · 4 PM"
  },
  {
    "name": "Mother's Ruin",
    "address": "1401 E 6th St Building A, Suite 204, Austin, TX 78702",
    "latitude": 30.263321899999998,
    "longitude": -97.7277282,
    "rating": 4.7,
    "reviews": 147,
    "type": "Bar",
    "distance": 0.96,
    "placeId": "ChIJ1975DHG1RIYRIxaYy7UTEVw",
    "phone": null,
    "website": "https://mothersruinaustin.com/",
    "hours": "Open · Closes 2 AM"
  },
  {
    "name": "Equipment Room",
    "address": "1101 Music Ln, Austin, TX 78704",
    "latitude": 30.2526807,
    "longitude": -97.7477179,
    "rating": 4.5,
    "reviews": 295,
    "type": "Bar",
    "distance": 1.04,
    "placeId": "ChIJMaJ0B3W1RIYRJzQI9f6yBIg",
    "phone": "(512) 520-5890",
    "website": "https://equipmentroom.com/",
    "hours": "Closed · Opens 5 PM"
  },
  {
    "name": "Otopia Rooftop Lounge",
    "address": "1901 San Antonio St Unit 1100, Austin, TX 78705",
    "latitude": 30.282409899999998,
    "longitude": -97.74288109999999,
    "rating": 4.9,
    "reviews": 1064,
    "type": "Bar",
    "distance": 1.05,
    "placeId": "ChIJQyqk37W1RIYRnCG26gFyqjc",
    "phone": "(737) 243-9040",
    "website": "https://www.otopiarooftop.com/?utm_source=google&utm_medium=organic&utm_campaign=business_listing",
    "hours": "Closed · Opens 5 PM"
  },
  {
    "name": "The Liberty",
    "address": "1618 E 6th St, Austin, TX 78702",
    "latitude": 30.2626529,
    "longitude": -97.7250954,
    "rating": 4.5,
    "reviews": 770,
    "type": "Bar",
    "distance": 1.12,
    "placeId": "ChIJ01xUKre1RIYRM_3DzIyLPT0",
    "phone": "(512) 514-0502",
    "website": null,
    "hours": "Opens soon · 4 PM"
  },
  {
    "name": "Yellow Jacket Social Club",
    "address": "1704 E 5th St., Austin, TX 78702",
    "latitude": 30.261727399999998,
    "longitude": -97.72463479999999,
    "rating": 4.5,
    "reviews": 953,
    "type": "Bar",
    "distance": 1.17,
    "placeId": "ChIJgS3Mxba1RIYRn89uoQtahTY",
    "phone": "(512) 480-9572",
    "website": "http://www.yellowjacketsocialclub.com/",
    "hours": "Open · Closes 2 AM"
  },
  {
    "name": "White Tiger",
    "address": "1321 S Congress Ave, Austin, TX 78704",
    "latitude": 30.2503133,
    "longitude": -97.7491185,
    "rating": 4.4,
    "reviews": 300,
    "type": "Bar",
    "distance": 1.22,
    "placeId": "ChIJWyzDNbe1RIYRQYsW6rGnggM",
    "phone": "(512) 893-7493",
    "website": null,
    "hours": "Open · Closes 12 AM"
  },
  {
    "name": "Whisler’s",
    "address": "1816 E 6th St, Austin, TX 78702",
    "latitude": 30.2619325,
    "longitude": -97.72273799999999,
    "rating": 4.6,
    "reviews": 1796,
    "type": "Bar",
    "distance": 1.27,
    "placeId": "ChIJ1wVp97a1RIYR6eeMLojxHYo",
    "phone": "(512) 480-0781",
    "website": "http://whislersatx.com/",
    "hours": "Opens soon · 4 PM"
  },
  {
    "name": "FOUR FIVE SIX",
    "address": "1910 E Cesar Chavez St, Austin, TX 78702",
    "latitude": 30.257168699999998,
    "longitude": -97.72374409999999,
    "rating": 4.7,
    "reviews": 48,
    "type": "Bar",
    "distance": 1.35,
    "placeId": "ChIJAfhZ9XO1RIYRqL_TR2GobbI",
    "phone": null,
    "website": null,
    "hours": "Open · Closes 2 AM"
  },
  {
    "name": "High Noon",
    "address": "2000 E Cesar Chavez St, Austin, TX 78702",
    "latitude": 30.2569503,
    "longitude": -97.72338859999999,
    "rating": 4.6,
    "reviews": 219,
    "type": "Bar",
    "distance": 1.37,
    "placeId": "ChIJ_T1PWOm1RIYRP4j7NbpRle8",
    "phone": null,
    "website": "http://www.highnoonaustin.com/",
    "hours": "Open · Closes 2 AM"
  },
  {
    "name": "Drinks Lounge",
    "address": "2001 E Cesar Chavez St, Austin, TX 78702",
    "latitude": 30.256419599999997,
    "longitude": -97.72326849999999,
    "rating": 4.5,
    "reviews": 572,
    "type": "Bar",
    "distance": 1.4,
    "placeId": "ChIJ84hf-rS1RIYRyN7KuJPZfT4",
    "phone": null,
    "website": "http://drinkslounge.com/",
    "hours": "Open · Closes 2 AM"
  },
  {
    "name": "watertrade",
    "address": "1603 S Congress Ave, Austin, TX 78704",
    "latitude": 30.2473651,
    "longitude": -97.7501159,
    "rating": 4.7,
    "reviews": 59,
    "type": "Bar",
    "distance": 1.43,
    "placeId": "ChIJCWV28GG1RIYRgQVJ_g48VJ0",
    "phone": "(512) 994-0428",
    "website": "http://otokoaustin.com/watertrade",
    "hours": "Closed · Opens 5 PM"
  },
  {
    "name": "Austin Daiquiri Factory",
    "address": "2000 E 12th St, Austin, TX 78702",
    "latitude": 30.2741042,
    "longitude": -97.718834,
    "rating": 4.9,
    "reviews": 454,
    "type": "Cocktail bar",
    "distance": 1.52,
    "placeId": "ChIJJWL23ei1RIYRMgj6v8IUVoU",
    "phone": "(512) 953-3519",
    "website": "http://www.austindaiquirifactory.com/",
    "hours": "Open · Closes 10 PM"
  },
  {
    "name": "Tiki Tatsu-Ya",
    "address": "1300 S Lamar Blvd, Austin, TX 78704",
    "latitude": 30.2538369,
    "longitude": -97.7633369,
    "rating": 4.5,
    "reviews": 1050,
    "type": "Tiki bar",
    "distance": 1.52,
    "placeId": "ChIJPZKeLri1RIYRz7_Szbsh93Q",
    "phone": "(512) 772-3700",
    "website": "https://www.tiki-tatsuya.com/",
    "hours": "Opens soon · 4 PM"
  },
  {
    "name": "The Wheel",
    "address": "1902 E Martin Luther King Jr Blvd B, Austin, TX 78702",
    "latitude": 30.2801609,
    "longitude": -97.72083169999999,
    "rating": 4.6,
    "reviews": 475,
    "type": "Cocktail bar",
    "distance": 1.6,
    "placeId": "ChIJ41uDJpW1RIYRat2eWrKra70",
    "phone": "(512) 531-9696",
    "website": "http://thewheelaustin.com/",
    "hours": "Opens soon · 4 PM"
  },
  {
    "name": "Kitty Cohen's",
    "address": "2211 Webberville Rd #3548, Austin, TX 78702",
    "latitude": 30.261790299999998,
    "longitude": -97.71640169999999,
    "rating": 4.5,
    "reviews": 965,
    "type": "Lounge bar",
    "distance": 1.64,
    "placeId": "ChIJm27hEsm1RIYRExVBdwnexSY",
    "phone": null,
    "website": "http://www.kittycohens.com/",
    "hours": "Open · Closes 2 AM"
  },
  {
    "name": "La Holly",
    "address": "2500 E 6th St, Austin, TX 78702",
    "latitude": 30.2590196,
    "longitude": -97.7144697,
    "rating": 4.6,
    "reviews": 358,
    "type": "Cocktail bar",
    "distance": 1.8,
    "placeId": "ChIJkZGXCsy1RIYRsVKLkJnXAx4",
    "phone": null,
    "website": "https://www.cantinaholly.com/",
    "hours": "Opens soon · 4 PM"
  },
  {
    "name": "Mama Dearest",
    "address": "515 Pedernales St, Austin, TX 78702",
    "latitude": 30.2584859,
    "longitude": -97.7146637,
    "rating": 4.7,
    "reviews": 211,
    "type": "Bar",
    "distance": 1.8,
    "placeId": "ChIJsTkU7zm1RIYR5_oWD8VVYTo",
    "phone": "(512) 402-8434",
    "website": "https://www.instagram.com/mamadearestatx?igsh=MXNkd282bnVvODAyaQ==",
    "hours": "Opens soon · 4 PM"
  },
  {
    "name": "The Austin Beer Garden Brewing Co.",
    "address": "1305 W Oltorf St, Austin, TX 78704",
    "latitude": 30.2453301,
    "longitude": -97.7688939,
    "rating": 4.6,
    "reviews": 1485,
    "type": "Brewpub",
    "distance": 2.16,
    "placeId": "ChIJs6-KANy0RIYRRTcMhnhoFaE",
    "phone": "(512) 298-2242",
    "website": "http://theabgb.com/",
    "hours": "Open · Closes 10 PM"
  },
  {
    "name": "Lustre Pearl East",
    "address": "114 Linden St, Austin, TX 78702",
    "latitude": 30.253006,
    "longitude": -97.7107398,
    "rating": 4.5,
    "reviews": 1223,
    "type": "Bar & grill",
    "distance": 2.17,
    "placeId": "ChIJcyktFKm1RIYRhoAuiJG50Zk",
    "phone": "(512) 524-1143",
    "website": "https://dunlapatx.com/lustre-pearl-east/",
    "hours": "Open · Closes 12 AM"
  },
  {
    "name": "Little Drinks Lounge",
    "address": "3801 S Congress Ave Suite 116, Austin, TX 78704",
    "latitude": 30.226822499999997,
    "longitude": -97.761444,
    "rating": 4.5,
    "reviews": 169,
    "type": "Bar",
    "distance": 3,
    "placeId": "ChIJmbJys8m1RIYR6XpYTNHXmqk",
    "phone": null,
    "website": "http://littledrinkslounge.com/",
    "hours": "Open · Closes 2 AM"
  },
  {
    "name": "Cosmic Pickle",
    "address": "121 Pickle Rd, Austin, TX 78704",
    "latitude": 30.226957,
    "longitude": -97.7624945,
    "rating": 4.7,
    "reviews": 4280,
    "type": "Bar",
    "distance": 3.01,
    "placeId": "ChIJA7CVXZW0RIYRVSZIlvlwJbA",
    "phone": "(512) 481-0694",
    "website": "https://www.cosmichospitalitygroup.com/",
    "hours": "Open · Closes 10 PM"
  },
  {
    "name": "The 04 Lounge",
    "address": "3808 S Congress Ave, Austin, TX 78704",
    "latitude": 30.225692799999997,
    "longitude": -97.7628075,
    "rating": 4.5,
    "reviews": 497,
    "type": "Bar",
    "distance": 3.1,
    "placeId": "ChIJFRl6m5W0RIYRtoxCMKCSwpk",
    "phone": "(512) 444-7788",
    "website": null,
    "hours": "Open · Closes 2 AM"
  },
  {
    "name": "Bender",
    "address": "321 W Ben White Blvd # 300, Austin, TX 78704",
    "latitude": 30.22428,
    "longitude": -97.76735699999999,
    "rating": 4.4,
    "reviews": 1111,
    "type": "Bar & grill",
    "distance": 3.3,
    "placeId": "ChIJr_7nl760RIYRfYIKToVECn8",
    "phone": "(512) 447-1800",
    "website": "http://www.benderbar.com/",
    "hours": "Open · Closes 2 AM"
  },
  {
    "name": "Pinthouse Brewing",
    "address": "2201 E Ben White Blvd, Austin, TX 78741",
    "latitude": 30.2153808,
    "longitude": -97.7423669,
    "rating": 4.7,
    "reviews": 1783,
    "type": "Brewpub",
    "distance": 3.58,
    "placeId": "ChIJm9HyQBu1RIYRjNu0JZnNP-U",
    "phone": "(512) 717-0873",
    "website": "https://pinthouse.com/?olonwp=JjBtp_vMLk25gkYh_bnoiQ",
    "hours": "Open · Closes 10 PM"
  },
  {
    "name": "The Skeleton Key",
    "address": "4720 S Congress Ave, Austin, TX 78745",
    "latitude": 30.2142603,
    "longitude": -97.76992899999999,
    "rating": 4.9,
    "reviews": 35,
    "type": "Bar",
    "distance": 3.99,
    "placeId": "ChIJRcFjJwC1RIYRjZZtdVO_LUQ",
    "phone": null,
    "website": "https://skeletonkeyaustin.com/",
    "hours": "Opens soon · 4 PM"
  },
  {
    "name": "Rusty Cannon Pub",
    "address": "730 W Stassney Ln #120, Austin, TX 78745",
    "latitude": 30.209985099999997,
    "longitude": -97.7825099,
    "rating": 4.3,
    "reviews": 766,
    "type": "Pub",
    "distance": 4.6,
    "placeId": "ChIJvxjQnau0RIYR1VaBXGLqsmM",
    "phone": "(512) 494-5271",
    "website": null,
    "hours": "Open · Closes 2 AM"
  },
  {
    "name": "FORTUNE TELLER",
    "address": "5604 S Congress Ave, Austin, TX 78745",
    "latitude": 30.2045629,
    "longitude": -97.7751691,
    "rating": 4.8,
    "reviews": 93,
    "type": "Bar",
    "distance": 4.73,
    "placeId": "ChIJv-HbdqSzRIYR9zErv-2lLhk",
    "phone": null,
    "website": "https://www.fortunetelleratx.com/",
    "hours": "Open · Closes 12 AM"
  },
  {
    "name": "Ojos Locos Sports Cantina (South Austin, TX)",
    "address": "901 Little Texas Ln Suite C, Austin, TX 78745",
    "latitude": 30.1972655,
    "longitude": -97.7670651,
    "rating": 4.3,
    "reviews": 521,
    "type": "Sports bar",
    "distance": 5.04,
    "placeId": "ChIJi-S0XgCzRIYR5becOcyKXj8",
    "phone": "(512) 813-7988",
    "website": "http://www.ojoslocos.com/",
    "hours": "Open · Closes 12 AM"
  },
  {
    "name": "The Little Darlin'",
    "address": "6507 Circle S Rd, Austin, TX 78745",
    "latitude": 30.194509099999998,
    "longitude": -97.7767964,
    "rating": 4.6,
    "reviews": 3219,
    "type": "American restaurant",
    "distance": 5.41,
    "placeId": "ChIJsdixM1CzRIYRqib6RW0vgww",
    "phone": "(512) 814-0999",
    "website": "http://thelittledarlin.com/",
    "hours": "Open · Closes 2 AM"
  },
  {
    "name": "Nomadic Outpost",
    "address": "3505 Country White Ln, Austin, TX 78749",
    "latitude": 30.221338,
    "longitude": -97.8265426,
    "rating": 4.7,
    "reviews": 229,
    "type": "Beer garden",
    "distance": 5.9,
    "placeId": "ChIJRTdVuYpLW4YR8WL80deeibI",
    "phone": "(512) 762-3994",
    "website": "https://www.nomadicbeergarden.com/",
    "hours": "Open · Closes 10 PM"
  },
  {
    "name": "W XYZ Bar & Lounge",
    "address": "6731 Legado Cir, Austin, TX 78749",
    "latitude": 30.221133299999998,
    "longitude": -97.8325885,
    "rating": 5,
    "reviews": 153,
    "type": "Bar",
    "distance": 6.22,
    "placeId": "ChIJZxP8X7NLW4YRaGFZO7KHVfM",
    "phone": "(512) 614-1010",
    "website": "https://www.marriott.com/en-us/hotels/auswa-aloft-austin-southwest/dining/",
    "hours": "Open · Closes 12 AM"
  },
  {
    "name": "Golden Hour Cafe & Wine Bar",
    "address": "7731 Menchaca Rd Suite 100, Austin, TX 78745",
    "latitude": 30.1937568,
    "longitude": -97.8106832,
    "rating": 4.5,
    "reviews": 169,
    "type": "Wine bar",
    "distance": 6.48,
    "placeId": "ChIJf0QRHKRNW4YRLPaxTpf0JfE",
    "phone": null,
    "website": "http://www.goldenhouratx.com/",
    "hours": "Open · Closes 9 PM"
  },
  {
    "name": "Buddy's Place",
    "address": "8619 Burnet Rd, Austin, TX 78757",
    "latitude": 30.3689808,
    "longitude": -97.7271971,
    "rating": 4.5,
    "reviews": 311,
    "type": "Bar",
    "distance": 7.1,
    "placeId": "ChIJJTt6L5bLRIYRaZoxmt8Fh-s",
    "phone": "(512) 459-4677",
    "website": "http://www.buddysplaceatx.com/",
    "hours": "Open · Closes 12 AM"
  },
  {
    "name": "El Oceano Sports Bar",
    "address": "9515 N Lamar Blvd Suite 102, Austin, TX 78753",
    "latitude": 30.365014799999997,
    "longitude": -97.69492699999999,
    "rating": 4.8,
    "reviews": 139,
    "type": "Bar & grill",
    "distance": 7.34,
    "placeId": "ChIJQfXiQPLJRIYRYu8Xcls7evI",
    "phone": "(512) 369-3346",
    "website": "https://eloceanosportbar.com/",
    "hours": "Open · Closes 12 AM"
  },
  {
    "name": "The Bon Aire",
    "address": "9070 Research Blvd #101, Austin, TX 78758",
    "latitude": 30.3734367,
    "longitude": -97.7283234,
    "rating": 4.6,
    "reviews": 449,
    "type": "Bar",
    "distance": 7.39,
    "placeId": "ChIJTRWi9hLLRIYRZ9Q6N7RjZu0",
    "phone": "(512) 284-7038",
    "website": "https://www.bonaireatx.com/",
    "hours": "Open · Closes 11 PM"
  },
  {
    "name": "Lala's South Pole",
    "address": "3008 Davis Ln #101, Austin, TX 78745",
    "latitude": 30.1910679,
    "longitude": -97.8320064,
    "rating": 4.5,
    "reviews": 102,
    "type": "Bar",
    "distance": 7.47,
    "placeId": "ChIJQSRiSKhNW4YReaC6xHzrWD0",
    "phone": "(512) 222-8214",
    "website": "http://lalassouthpole.com/",
    "hours": "Open · Closes 12 AM"
  },
  {
    "name": "Vincent's",
    "address": "8916 Brodie Ln #100, Austin, TX 78748",
    "latitude": 30.1947343,
    "longitude": -97.84350719999999,
    "rating": 4.3,
    "reviews": 671,
    "type": "Sports bar",
    "distance": 7.81,
    "placeId": "ChIJ__9PNnFMW4YRjKITXe7hPw0",
    "phone": "(512) 291-2845",
    "website": "http://www.vincentspub.com/",
    "hours": "Open · Closes 12 AM"
  },
  {
    "name": "Turnstile Bar and Restaurant",
    "address": "10025 Burnet Rd, Austin, TX 78758",
    "latitude": 30.384066599999997,
    "longitude": -97.72336489999999,
    "rating": 4.7,
    "reviews": 733,
    "type": "Restaurant",
    "distance": 8.16,
    "placeId": "ChIJj4J4QkrLRIYR3VD-TIG2grk",
    "phone": "(512) 373-3273",
    "website": "http://www.turnstilebrews.com/",
    "hours": "Open · Closes 12 AM"
  },
  {
    "name": "Kramer's Cocktails",
    "address": "2307 Kramer Ln, Austin, TX 78758",
    "latitude": 30.391033699999998,
    "longitude": -97.71455759999999,
    "rating": 4.6,
    "reviews": 45,
    "type": "Cocktail bar",
    "distance": 8.72,
    "placeId": "ChIJxwo-HRHLRIYRqQeGCtMzGUU",
    "phone": null,
    "website": "http://kramersatx.com/",
    "hours": "Opens soon · 4 PM"
  },
  {
    "name": "Bouldin Acres",
    "address": "1806 W Braker Ln, Austin, TX 78758",
    "latitude": 30.3912908,
    "longitude": -97.7049189,
    "rating": 4.2,
    "reviews": 380,
    "type": "Beer garden",
    "distance": 8.87,
    "placeId": "ChIJvVDq0bjLRIYRN_PpIHzzI0c",
    "phone": "(737) 284-3404",
    "website": "http://braker.bouldinacres.com/",
    "hours": "Open · Closes 11 PM"
  },
  {
    "name": "Walnut Creek Pub",
    "address": "11806 N Lamar Blvd, Austin, TX 78753",
    "latitude": 30.389028699999997,
    "longitude": -97.68355249999999,
    "rating": 4.6,
    "reviews": 148,
    "type": "Pub",
    "distance": 9.14,
    "placeId": "ChIJ61HnOu7JRIYR3OAan3kDIyA",
    "phone": "(512) 284-9833",
    "website": "http://walnutcreekpub.com/",
    "hours": "Open · Closes 2 AM"
  },
  {
    "name": "Corinne at The Domain",
    "address": "11301 Domain Dr, Austin, TX 78758",
    "latitude": 30.399258,
    "longitude": -97.7246006,
    "rating": 4.8,
    "reviews": 1306,
    "type": "Bar",
    "distance": 9.19,
    "placeId": "ChIJq6rqw3PMRIYRXahNpj8DwcE",
    "phone": "(512) 687-9313",
    "website": "https://www.corinneatxdomain.com/?utm_source=google&utm_medium=organic&utm_campaign=business_listing",
    "hours": "Closes soon · 4 PM · Reopens 5 PM"
  },
  {
    "name": "Lavaca Street Bar - Rock Rose",
    "address": "11420 Rock Rose Ave #100, Austin, TX 78758",
    "latitude": 30.4005853,
    "longitude": -97.72315569999999,
    "rating": 4.3,
    "reviews": 848,
    "type": "Bar",
    "distance": 9.29,
    "placeId": "ChIJ3XrPgnLMRIYRq6P7aTCi_dw",
    "phone": "(512) 575-4428",
    "website": "https://lavacastdomain.com/",
    "hours": "Open · Closes 2 AM"
  },
  {
    "name": "77° Rooftop Patio Bar",
    "address": "11500 Rock Rose Ave, Austin, TX 78758",
    "latitude": 30.4013556,
    "longitude": -97.7228167,
    "rating": 4.2,
    "reviews": 989,
    "type": "Bar",
    "distance": 9.35,
    "placeId": "ChIJ7aKiX3LMRIYRwQJOksFSz7k",
    "phone": "(512) 589-2925",
    "website": "http://77-degrees.com/",
    "hours": "Open · Closes 2 AM"
  },
  {
    "name": "Wonder Bar",
    "address": "11500 Rock Rose Ave suite d, Austin, TX 78758",
    "latitude": 30.401482599999998,
    "longitude": -97.7227648,
    "rating": 4.3,
    "reviews": 1107,
    "type": "Bar",
    "distance": 9.36,
    "placeId": "ChIJl9essuLNRIYRBPEV9sPVDtU",
    "phone": "(512) 659-5537",
    "website": "http://wonderbaratx.com/",
    "hours": "Open · Closes 2 AM"
  },
  {
    "name": "AKB, a hotel bar",
    "address": "3121 Palm Way #101, Austin, TX 78758",
    "latitude": 30.4023111,
    "longitude": -97.7212167,
    "rating": 4.4,
    "reviews": 104,
    "type": "Bar",
    "distance": 9.43,
    "placeId": "ChIJP2ns6u_NRIYRwX-n7QZh8WU",
    "phone": "(737) 300-4800",
    "website": "https://www.akbhotelbar.com/location/austin?utm_source=google&utm_medium=organic&utm_campaign=business_listing",
    "hours": "Open · Closes 11 PM"
  },
  {
    "name": "WXYZ Bar",
    "address": "11601 Domain Dr, Austin, TX 78758",
    "latitude": 30.402766,
    "longitude": -97.72374579999999,
    "rating": 4.4,
    "reviews": 30,
    "type": "Bar",
    "distance": 9.44,
    "placeId": "ChIJVYBks1_NRIYR8uztIrOlcqU",
    "phone": "(512) 491-0777",
    "website": "https://www.marriott.com/en-us/hotels/ausal-aloft-austin-at-the-domain/overview/",
    "hours": "Closed · Opens 5 PM"
  },
  {
    "name": "Doc B's Restaurant",
    "address": "3001 Palm Way Suite 120, Austin, TX 78758",
    "latitude": 30.4027556,
    "longitude": -97.7197442,
    "rating": 4.7,
    "reviews": 3366,
    "type": "Bar",
    "distance": 9.47,
    "placeId": "ChIJiSgwmnLMRIYRifsgXKrwVSQ",
    "phone": "(512) 672-8400",
    "website": "https://docbsrestaurant.com/locations/austin",
    "hours": "Open · Closes 10 PM"
  },
  {
    "name": "Culinary Dropout",
    "address": "11721 Rock Rose Ave #100, Austin, TX 78758",
    "latitude": 30.4034725,
    "longitude": -97.7215123,
    "rating": 4.4,
    "reviews": 6049,
    "type": "Bar",
    "distance": 9.5,
    "placeId": "ChIJ1eAeVnLMRIYR_VB5FIj_LuE",
    "phone": "(512) 777-3394",
    "website": "https://www.culinarydropout.com/locations/austin-tx/?utm_source=Google&utm_medium=Organic&utm_campaign=Maps",
    "hours": "Open · Closes 11 PM"
  },
  {
    "name": "Canary Roost",
    "address": "11900 Metric Blvd, Austin, TX 78758",
    "latitude": 30.4004731,
    "longitude": -97.7039135,
    "rating": 4.2,
    "reviews": 583,
    "type": "Bar",
    "distance": 9.5,
    "placeId": "ChIJQ87gdQTMRIYR8XapFxvFGKg",
    "phone": "(512) 836-6360",
    "website": null,
    "hours": "Open · Closes 2 AM"
  },
  {
    "name": "The Draft Shack",
    "address": "11920 Domain Dr, Austin, TX 78758",
    "latitude": 30.4062739,
    "longitude": -97.7200191,
    "rating": 4.5,
    "reviews": 76,
    "type": "Bar",
    "distance": 9.71,
    "placeId": "ChIJn1vX1WzMRIYRaKX2uV_oqro",
    "phone": "(512) 831-3981",
    "website": "http://www.wholefoodsmarket.com/stores/domain?utm_source=google&utm_medium=organic&utm_campaign=listings",
    "hours": "Open · Closes 9 PM"
  },
  {
    "name": "The Hideout Pub",
    "address": "12164 State Hwy 1 Loop, Austin, TX 78758",
    "latitude": 30.4124919,
    "longitude": -97.7097726,
    "rating": 4.4,
    "reviews": 1288,
    "type": "Bar",
    "distance": 10.23,
    "placeId": "ChIJHV-EeRfMRIYRAuCfqGPsSnw",
    "phone": "(512) 821-9093",
    "website": "http://thehideoutpub.com/",
    "hours": "Open · Closes 2 AM"
  },
  {
    "name": "Parmer Lane Tavern",
    "address": "2121 W Parmer Ln, Austin, TX 78727",
    "latitude": 30.4153576,
    "longitude": -97.69665529999999,
    "rating": 4.2,
    "reviews": 430,
    "type": "Bar",
    "distance": 10.61,
    "placeId": "ChIJA_wSHKDORIYRqLMpKvn21G0",
    "phone": "(512) 520-9136",
    "website": "http://www.parmerlanetavern.com/",
    "hours": "Open · Closes 2 AM"
  },
  {
    "name": "Uptown Lounge Craft Kitchen & Cocktails",
    "address": "13205 Burnet Rd, Austin, TX 78727",
    "latitude": 30.431998099999998,
    "longitude": -97.69846489999999,
    "rating": 4.6,
    "reviews": 30,
    "type": "Bar",
    "distance": 11.69,
    "placeId": "ChIJVRV1coLORIYRg5mDWq0_NhE",
    "phone": "(512) 580-2847",
    "website": "https://www.choicehotels.com/texas/austin/cambria-hotels/txi94",
    "hours": "Opens soon · 4 PM"
  }
]